MANIFEST.in
README.md
setup.py
bci_pacman/__init__.py
bci_pacman/_version.txt
bci_pacman.egg-info/PKG-INFO
bci_pacman.egg-info/SOURCES.txt
bci_pacman.egg-info/dependency_links.txt
bci_pacman.egg-info/requires.txt
bci_pacman.egg-info/top_level.txt
bci_pacman/envs/__init__.py
bci_pacman/envs/game.py
bci_pacman/envs/ghostAgents.py
bci_pacman/envs/graphicsDisplay.py
bci_pacman/envs/graphicsUtils.py
bci_pacman/envs/layout.py
bci_pacman/envs/pacman.py
bci_pacman/envs/pacmanAgents.py
bci_pacman/envs/pacman_env.py
bci_pacman/envs/util.py
bci_pacman/layouts/capsuleClassic.lay
bci_pacman/layouts/capsuleClassic_noGhosts.lay
bci_pacman/layouts/contestClassic.lay
bci_pacman/layouts/contestClassic_noGhosts.lay
bci_pacman/layouts/generate_layouts.py
bci_pacman/layouts/mediumClassic.lay
bci_pacman/layouts/mediumClassic_noGhosts.lay
bci_pacman/layouts/mediumGrid.lay
bci_pacman/layouts/mediumGrid_noGhosts.lay
bci_pacman/layouts/minimaxClassic.lay
bci_pacman/layouts/minimaxClassic_noGhosts.lay
bci_pacman/layouts/openClassic.lay
bci_pacman/layouts/openClassic_noGhosts.lay
bci_pacman/layouts/originalClassic.lay
bci_pacman/layouts/originalClassic_noGhosts.lay
bci_pacman/layouts/random7x7_1.lay
bci_pacman/layouts/random7x7_10.lay
bci_pacman/layouts/random7x7_2.lay
bci_pacman/layouts/random7x7_3.lay
bci_pacman/layouts/random7x7_4.lay
bci_pacman/layouts/random7x7_5.lay
bci_pacman/layouts/random7x7_6.lay
bci_pacman/layouts/random7x7_7.lay
bci_pacman/layouts/random7x7_8.lay
bci_pacman/layouts/random7x7_9.lay
bci_pacman/layouts/smallClassic.lay
bci_pacman/layouts/smallClassic_noGhosts.lay
bci_pacman/layouts/smallGrid.lay
bci_pacman/layouts/smallGrid_noGhosts.lay
bci_pacman/layouts/testClassic.lay
bci_pacman/layouts/testClassic_noGhosts.lay
bci_pacman/layouts/trappedClassic.lay
bci_pacman/layouts/trappedClassic_noGhosts.lay
bci_pacman/layouts/trickyClassic.lay
bci_pacman/layouts/trickyClassic_noGhosts.lay