Metadata-Version: 1.2
Name: bci-pacman
Version: 0.1
Summary: GCPDS: Scripts for test BCI with Pacman.
Home-page: UNKNOWN
Author: Yeison Cardona
Author-email: yeisoneng@gmail.com
Maintainer: Yeison Cardona
Maintainer-email: yeisoneng@gmail.com
License: BSD License
Download-URL: https://bitbucket.org/gcpds/bci_pacman/downloads/
Platform: UNKNOWN
